MANIFEST.in
README.md
setup.py
phone/__init__.py
phone/build_record.py
phone/phone.dat
phone/phone.py
phone/test_phone.py
phone.egg-info/PKG-INFO
phone.egg-info/SOURCES.txt
phone.egg-info/dependency_links.txt
phone.egg-info/not-zip-safe
phone.egg-info/top_level.txt