Metadata-Version: 1.1
Name: phone
Version: 0.4.5
Summary: 手机号码库
Home-page: https://github.com/ls0f/phone
Author: ls0f
Author-email: admin@lovedboy.com
License: BSD
Platform: UNKNOWN
Classifier: License :: OSI Approved :: MIT License
Classifier: Programming Language :: Python
Classifier: Intended Audience :: Developers
Classifier: Operating System :: OS Independent
